[{"Index":1,"PositionX":73,"PositionY":4,"Direction":0},{"Index":1,"PositionX":74,"PositionY":4,"Direction":0},{"Index":1,"PositionX":75,"PositionY":4,"Direction":0},{"Index":1,"PositionX":76,"PositionY":4,"Direction":0},{"Index":1,"PositionX":77,"PositionY":4,"Direction":0},{"Index":1,"PositionX":78,"PositionY":4,"Direction":0},{"Index":1,"PositionX":79,"PositionY":4,"Direction":0},{"Index":1,"PositionX":80,"PositionY":4,"Direction":0},{"Index":1,"PositionX":81,"PositionY":4,"Direction":0},{"Index":1,"PositionX":82,"PositionY":4,"Direction":0},{"Index":1,"PositionX":83,"PositionY":4,"Direction":0},{"Index":1,"PositionX":73,"PositionY":5,"Direction":0},{"Index":1,"PositionX":74,"PositionY":5,"Direction":0},{"Index":1,"PositionX":75,"PositionY":5,"Direction":0},{"Index":1,"PositionX":76,"PositionY":5,"Direction":0},{"Index":1,"PositionX":77,"PositionY":5,"Direction":0},{"Index":1,"PositionX":78,"PositionY":5,"Direction":0},{"Index":1,"PositionX":79,"PositionY":5,"Direction":0},{"Index":1,"PositionX":80,"PositionY":5,"Direction":0},{"Index":1,"PositionX":81,"PositionY":5,"Direction":0},{"Index":1,"PositionX":82,"PositionY":5,"Direction":0},{"Index":1,"PositionX":83,"PositionY":5,"Direction":0},{"Index":1,"PositionX":84,"PositionY":5,"Direction":0},{"Index":1,"PositionX":85,"PositionY":5,"Direction":0},{"Index":1,"PositionX":86,"PositionY":5,"Direction":0},{"Index":1,"PositionX":87,"PositionY":5,"Direction":0},{"Index":1,"PositionX":88,"PositionY":5,"Direction":0},{"Index":1,"PositionX":89,"PositionY":5,"Direction":0},{"Index":1,"PositionX":90,"PositionY":5,"Direction":0},{"Index":1,"PositionX":91,"PositionY":5,"Direction":0},{"Index":1,"PositionX":73,"PositionY":6,"Direction":0},{"Index":1,"PositionX":74,"PositionY":6,"Direction":0},{"Index":1,"PositionX":75,"PositionY":6,"Direction":0},{"Index":1,"PositionX":76,"PositionY":6,"Direction":0},{"Index":1,"PositionX":77,"PositionY":6,"Direction":0},{"Index":1,"PositionX":78,"PositionY":6,"Direction":0},{"Index":1,"PositionX":79,"PositionY":6,"Direction":0},{"Index":1,"PositionX":80,"PositionY":6,"Direction":0},{"Index":1,"PositionX":81,"PositionY":6,"Direction":0},{"Index":1,"PositionX":82,"PositionY":6,"Direction":0},{"Index":1,"PositionX":83,"PositionY":6,"Direction":0},{"Index":1,"PositionX":84,"PositionY":6,"Direction":0},{"Index":1,"PositionX":85,"PositionY":6,"Direction":0},{"Index":1,"PositionX":86,"PositionY":6,"Direction":0},{"Index":1,"PositionX":87,"PositionY":6,"Direction":0},{"Index":1,"PositionX":88,"PositionY":6,"Direction":0},{"Index":1,"PositionX":89,"PositionY":6,"Direction":0},{"Index":1,"PositionX":90,"PositionY":6,"Direction":0},{"Index":1,"PositionX":91,"PositionY":6,"Direction":0},{"Index":1,"PositionX":92,"PositionY":6,"Direction":0},{"Index":1,"PositionX":93,"PositionY":6,"Direction":0},{"Index":1,"PositionX":94,"PositionY":6,"Direction":0},{"Index":1,"PositionX":95,"PositionY":6,"Direction":0},{"Index":1,"PositionX":96,"PositionY":6,"Direction":0},{"Index":1,"PositionX":97,"PositionY":6,"Direction":0},{"Index":1,"PositionX":73,"PositionY":7,"Direction":0},{"Index":1,"PositionX":74,"PositionY":7,"Direction":0},{"Index":1,"PositionX":75,"PositionY":7,"Direction":0},{"Index":1,"PositionX":76,"PositionY":7,"Direction":0},{"Index":1,"PositionX":77,"PositionY":7,"Direction":0},{"Index":1,"PositionX":78,"PositionY":7,"Direction":0},{"Index":1,"PositionX":79,"PositionY":7,"Direction":0},{"Index":1,"PositionX":80,"PositionY":7,"Direction":0},{"Index":1,"PositionX":81,"PositionY":7,"Direction":0},{"Index":1,"PositionX":82,"PositionY":7,"Direction":0},{"Index":1,"PositionX":83,"PositionY":7,"Direction":0},{"Index":1,"PositionX":84,"PositionY":7,"Direction":0},{"Index":1,"PositionX":85,"PositionY":7,"Direction":0},{"Index":1,"PositionX":86,"PositionY":7,"Direction":0},{"Index":1,"PositionX":87,"PositionY":7,"Direction":0},{"Index":1,"PositionX":88,"PositionY":7,"Direction":0},{"Index":1,"PositionX":89,"PositionY":7,"Direction":0},{"Index":1,"PositionX":90,"PositionY":7,"Direction":0},{"Index":1,"PositionX":91,"PositionY":7,"Direction":0},{"Index":1,"PositionX":92,"PositionY":7,"Direction":0},{"Index":1,"PositionX":93,"PositionY":7,"Direction":0},{"Index":1,"PositionX":94,"PositionY":7,"Direction":0},{"Index":1,"PositionX":95,"PositionY":7,"Direction":0},{"Index":1,"PositionX":96,"PositionY":7,"Direction":0},{"Index":1,"PositionX":97,"PositionY":7,"Direction":0},{"Index":1,"PositionX":73,"PositionY":8,"Direction":0},{"Index":1,"PositionX":74,"PositionY":8,"Direction":0},{"Index":1,"PositionX":75,"PositionY":8,"Direction":0},{"Index":1,"PositionX":76,"PositionY":8,"Direction":0},{"Index":1,"PositionX":77,"PositionY":8,"Direction":0},{"Index":1,"PositionX":78,"PositionY":8,"Direction":0},{"Index":1,"PositionX":79,"PositionY":8,"Direction":0},{"Index":1,"PositionX":80,"PositionY":8,"Direction":0},{"Index":1,"PositionX":81,"PositionY":8,"Direction":0},{"Index":1,"PositionX":82,"PositionY":8,"Direction":0},{"Index":1,"PositionX":83,"PositionY":8,"Direction":0},{"Index":1,"PositionX":84,"PositionY":8,"Direction":0},{"Index":1,"PositionX":85,"PositionY":8,"Direction":0},{"Index":1,"PositionX":86,"PositionY":8,"Direction":0},{"Index":1,"PositionX":87,"PositionY":8,"Direction":0},{"Index":1,"PositionX":88,"PositionY":8,"Direction":0},{"Index":1,"PositionX":89,"PositionY":8,"Direction":0},{"Index":1,"PositionX":90,"PositionY":8,"Direction":0},{"Index":1,"PositionX":91,"PositionY":8,"Direction":0},{"Index":1,"PositionX":92,"PositionY":8,"Direction":0},{"Index":1,"PositionX":93,"PositionY":8,"Direction":0},{"Index":1,"PositionX":94,"PositionY":8,"Direction":0},{"Index":1,"PositionX":95,"PositionY":8,"Direction":0},{"Index":1,"PositionX":96,"PositionY":8,"Direction":0},{"Index":1,"PositionX":97,"PositionY":8,"Direction":0},{"Index":1,"PositionX":73,"PositionY":9,"Direction":0},{"Index":1,"PositionX":74,"PositionY":9,"Direction":0},{"Index":1,"PositionX":75,"PositionY":9,"Direction":0},{"Index":1,"PositionX":76,"PositionY":9,"Direction":0},{"Index":1,"PositionX":77,"PositionY":9,"Direction":0},{"Index":1,"PositionX":78,"PositionY":9,"Direction":0},{"Index":1,"PositionX":79,"PositionY":9,"Direction":0},{"Index":1,"PositionX":80,"PositionY":9,"Direction":0},{"Index":1,"PositionX":81,"PositionY":9,"Direction":0},{"Index":1,"PositionX":82,"PositionY":9,"Direction":0},{"Index":1,"PositionX":83,"PositionY":9,"Direction":0},{"Index":1,"PositionX":84,"PositionY":9,"Direction":0},{"Index":1,"PositionX":85,"PositionY":9,"Direction":0},{"Index":1,"PositionX":86,"PositionY":9,"Direction":0},{"Index":1,"PositionX":87,"PositionY":9,"Direction":0},{"Index":1,"PositionX":88,"PositionY":9,"Direction":0},{"Index":1,"PositionX":89,"PositionY":9,"Direction":0},{"Index":1,"PositionX":90,"PositionY":9,"Direction":0},{"Index":1,"PositionX":91,"PositionY":9,"Direction":0},{"Index":1,"PositionX":92,"PositionY":9,"Direction":0},{"Index":1,"PositionX":93,"PositionY":9,"Direction":0},{"Index":1,"PositionX":94,"PositionY":9,"Direction":0},{"Index":1,"PositionX":95,"PositionY":9,"Direction":0},{"Index":1,"PositionX":96,"PositionY":9,"Direction":0},{"Index":1,"PositionX":97,"PositionY":9,"Direction":0},{"Index":1,"PositionX":73,"PositionY":10,"Direction":0},{"Index":1,"PositionX":74,"PositionY":10,"Direction":0},{"Index":1,"PositionX":75,"PositionY":10,"Direction":0},{"Index":1,"PositionX":76,"PositionY":10,"Direction":0},{"Index":1,"PositionX":77,"PositionY":10,"Direction":0},{"Index":1,"PositionX":78,"PositionY":10,"Direction":0},{"Index":1,"PositionX":79,"PositionY":10,"Direction":0},{"Index":1,"PositionX":80,"PositionY":10,"Direction":0},{"Index":1,"PositionX":81,"PositionY":10,"Direction":0},{"Index":1,"PositionX":82,"PositionY":10,"Direction":0},{"Index":1,"PositionX":83,"PositionY":10,"Direction":0},{"Index":1,"PositionX":84,"PositionY":10,"Direction":0},{"Index":1,"PositionX":85,"PositionY":10,"Direction":0},{"Index":1,"PositionX":86,"PositionY":10,"Direction":0},{"Index":1,"PositionX":87,"PositionY":10,"Direction":0},{"Index":1,"PositionX":88,"PositionY":10,"Direction":0},{"Index":1,"PositionX":89,"PositionY":10,"Direction":0},{"Index":1,"PositionX":90,"PositionY":10,"Direction":0},{"Index":1,"PositionX":91,"PositionY":10,"Direction":0},{"Index":1,"PositionX":92,"PositionY":10,"Direction":0},{"Index":1,"PositionX":93,"PositionY":10,"Direction":0},{"Index":1,"PositionX":94,"PositionY":10,"Direction":0},{"Index":1,"PositionX":95,"PositionY":10,"Direction":0},{"Index":1,"PositionX":96,"PositionY":10,"Direction":0},{"Index":1,"PositionX":97,"PositionY":10,"Direction":0},{"Index":1,"PositionX":73,"PositionY":11,"Direction":0},{"Index":1,"PositionX":74,"PositionY":11,"Direction":0},{"Index":1,"PositionX":75,"PositionY":11,"Direction":0},{"Index":1,"PositionX":76,"PositionY":11,"Direction":0},{"Index":1,"PositionX":77,"PositionY":11,"Direction":0},{"Index":1,"PositionX":78,"PositionY":11,"Direction":0},{"Index":1,"PositionX":79,"PositionY":11,"Direction":0},{"Index":1,"PositionX":80,"PositionY":11,"Direction":0},{"Index":1,"PositionX":81,"PositionY":11,"Direction":0},{"Index":1,"PositionX":82,"PositionY":11,"Direction":0},{"Index":1,"PositionX":83,"PositionY":11,"Direction":0},{"Index":1,"PositionX":84,"PositionY":11,"Direction":0},{"Index":1,"PositionX":85,"PositionY":11,"Direction":0},{"Index":1,"PositionX":86,"PositionY":11,"Direction":0},{"Index":1,"PositionX":87,"PositionY":11,"Direction":0},{"Index":1,"PositionX":88,"PositionY":11,"Direction":0},{"Index":1,"PositionX":89,"PositionY":11,"Direction":0},{"Index":1,"PositionX":90,"PositionY":11,"Direction":0},{"Index":1,"PositionX":91,"PositionY":11,"Direction":0},{"Index":1,"PositionX":92,"PositionY":11,"Direction":0},{"Index":1,"PositionX":93,"PositionY":11,"Direction":0},{"Index":1,"PositionX":94,"PositionY":11,"Direction":0},{"Index":1,"PositionX":95,"PositionY":11,"Direction":0},{"Index":1,"PositionX":96,"PositionY":11,"Direction":0},{"Index":1,"PositionX":97,"PositionY":11,"Direction":0},{"Index":1,"PositionX":73,"PositionY":12,"Direction":0},{"Index":1,"PositionX":74,"PositionY":12,"Direction":0},{"Index":1,"PositionX":75,"PositionY":12,"Direction":0},{"Index":1,"PositionX":76,"PositionY":12,"Direction":0},{"Index":1,"PositionX":77,"PositionY":12,"Direction":0},{"Index":1,"PositionX":78,"PositionY":12,"Direction":0},{"Index":1,"PositionX":79,"PositionY":12,"Direction":0},{"Index":1,"PositionX":80,"PositionY":12,"Direction":0},{"Index":1,"PositionX":81,"PositionY":12,"Direction":0},{"Index":1,"PositionX":82,"PositionY":12,"Direction":0},{"Index":1,"PositionX":83,"PositionY":12,"Direction":0},{"Index":1,"PositionX":84,"PositionY":12,"Direction":0},{"Index":1,"PositionX":85,"PositionY":12,"Direction":0},{"Index":1,"PositionX":86,"PositionY":12,"Direction":0},{"Index":1,"PositionX":87,"PositionY":12,"Direction":0},{"Index":1,"PositionX":88,"PositionY":12,"Direction":0},{"Index":1,"PositionX":89,"PositionY":12,"Direction":0},{"Index":1,"PositionX":90,"PositionY":12,"Direction":0},{"Index":1,"PositionX":91,"PositionY":12,"Direction":0},{"Index":1,"PositionX":92,"PositionY":12,"Direction":0},{"Index":1,"PositionX":93,"PositionY":12,"Direction":0},{"Index":1,"PositionX":94,"PositionY":12,"Direction":0},{"Index":1,"PositionX":95,"PositionY":12,"Direction":0},{"Index":1,"PositionX":96,"PositionY":12,"Direction":0},{"Index":1,"PositionX":97,"PositionY":12,"Direction":0},{"Index":1,"PositionX":73,"PositionY":13,"Direction":0},{"Index":1,"PositionX":74,"PositionY":13,"Direction":0},{"Index":1,"PositionX":75,"PositionY":13,"Direction":0},{"Index":1,"PositionX":76,"PositionY":13,"Direction":0},{"Index":1,"PositionX":77,"PositionY":13,"Direction":0},{"Index":1,"PositionX":78,"PositionY":13,"Direction":0},{"Index":1,"PositionX":79,"PositionY":13,"Direction":0},{"Index":1,"PositionX":80,"PositionY":13,"Direction":0},{"Index":1,"PositionX":81,"PositionY":13,"Direction":0},{"Index":1,"PositionX":82,"PositionY":13,"Direction":0},{"Index":1,"PositionX":83,"PositionY":13,"Direction":0},{"Index":1,"PositionX":84,"PositionY":13,"Direction":0},{"Index":1,"PositionX":85,"PositionY":13,"Direction":0},{"Index":1,"PositionX":86,"PositionY":13,"Direction":0},{"Index":1,"PositionX":87,"PositionY":13,"Direction":0},{"Index":1,"PositionX":88,"PositionY":13,"Direction":0},{"Index":1,"PositionX":89,"PositionY":13,"Direction":0},{"Index":1,"PositionX":90,"PositionY":13,"Direction":0},{"Index":1,"PositionX":91,"PositionY":13,"Direction":0},{"Index":1,"PositionX":92,"PositionY":13,"Direction":0},{"Index":1,"PositionX":93,"PositionY":13,"Direction":0},{"Index":1,"PositionX":94,"PositionY":13,"Direction":0},{"Index":1,"PositionX":95,"PositionY":13,"Direction":0},{"Index":1,"PositionX":96,"PositionY":13,"Direction":0},{"Index":1,"PositionX":97,"PositionY":13,"Direction":0},{"Index":1,"PositionX":73,"PositionY":14,"Direction":0},{"Index":1,"PositionX":74,"PositionY":14,"Direction":0},{"Index":1,"PositionX":75,"PositionY":14,"Direction":0},{"Index":1,"PositionX":76,"PositionY":14,"Direction":0},{"Index":1,"PositionX":77,"PositionY":14,"Direction":0},{"Index":1,"PositionX":78,"PositionY":14,"Direction":0},{"Index":1,"PositionX":79,"PositionY":14,"Direction":0},{"Index":1,"PositionX":80,"PositionY":14,"Direction":0},{"Index":1,"PositionX":81,"PositionY":14,"Direction":0},{"Index":1,"PositionX":82,"PositionY":14,"Direction":0},{"Index":1,"PositionX":83,"PositionY":14,"Direction":0},{"Index":1,"PositionX":84,"PositionY":14,"Direction":0},{"Index":1,"PositionX":85,"PositionY":14,"Direction":0},{"Index":1,"PositionX":86,"PositionY":14,"Direction":0},{"Index":1,"PositionX":87,"PositionY":14,"Direction":0},{"Index":1,"PositionX":88,"PositionY":14,"Direction":0},{"Index":1,"PositionX":89,"PositionY":14,"Direction":0},{"Index":1,"PositionX":90,"PositionY":14,"Direction":0},{"Index":1,"PositionX":91,"PositionY":14,"Direction":0},{"Index":1,"PositionX":92,"PositionY":14,"Direction":0},{"Index":1,"PositionX":93,"PositionY":14,"Direction":0},{"Index":1,"PositionX":94,"PositionY":14,"Direction":0},{"Index":1,"PositionX":95,"PositionY":14,"Direction":0},{"Index":1,"PositionX":96,"PositionY":14,"Direction":0},{"Index":1,"PositionX":97,"PositionY":14,"Direction":0},{"Index":1,"PositionX":74,"PositionY":15,"Direction":0},{"Index":1,"PositionX":75,"PositionY":15,"Direction":0},{"Index":1,"PositionX":76,"PositionY":15,"Direction":0},{"Index":1,"PositionX":77,"PositionY":15,"Direction":0},{"Index":1,"PositionX":78,"PositionY":15,"Direction":0},{"Index":1,"PositionX":79,"PositionY":15,"Direction":0},{"Index":1,"PositionX":80,"PositionY":15,"Direction":0},{"Index":1,"PositionX":81,"PositionY":15,"Direction":0},{"Index":1,"PositionX":82,"PositionY":15,"Direction":0},{"Index":1,"PositionX":83,"PositionY":15,"Direction":0},{"Index":1,"PositionX":84,"PositionY":15,"Direction":0},{"Index":1,"PositionX":85,"PositionY":15,"Direction":0},{"Index":1,"PositionX":86,"PositionY":15,"Direction":0},{"Index":1,"PositionX":87,"PositionY":15,"Direction":0},{"Index":1,"PositionX":88,"PositionY":15,"Direction":0},{"Index":1,"PositionX":89,"PositionY":15,"Direction":0},{"Index":1,"PositionX":90,"PositionY":15,"Direction":0},{"Index":1,"PositionX":91,"PositionY":15,"Direction":0},{"Index":1,"PositionX":92,"PositionY":15,"Direction":0},{"Index":1,"PositionX":93,"PositionY":15,"Direction":0},{"Index":1,"PositionX":94,"PositionY":15,"Direction":0},{"Index":1,"PositionX":95,"PositionY":15,"Direction":0},{"Index":1,"PositionX":96,"PositionY":15,"Direction":0},{"Index":1,"PositionX":97,"PositionY":15,"Direction":0},{"Index":1,"PositionX":74,"PositionY":16,"Direction":0},{"Index":1,"PositionX":75,"PositionY":16,"Direction":0},{"Index":1,"PositionX":76,"PositionY":16,"Direction":0},{"Index":1,"PositionX":77,"PositionY":16,"Direction":0},{"Index":1,"PositionX":78,"PositionY":16,"Direction":0},{"Index":1,"PositionX":79,"PositionY":16,"Direction":0},{"Index":1,"PositionX":80,"PositionY":16,"Direction":0},{"Index":1,"PositionX":81,"PositionY":16,"Direction":0},{"Index":1,"PositionX":82,"PositionY":16,"Direction":0},{"Index":1,"PositionX":83,"PositionY":16,"Direction":0},{"Index":1,"PositionX":84,"PositionY":16,"Direction":0},{"Index":1,"PositionX":85,"PositionY":16,"Direction":0},{"Index":1,"PositionX":87,"PositionY":16,"Direction":0},{"Index":1,"PositionX":88,"PositionY":16,"Direction":0},{"Index":1,"PositionX":89,"PositionY":16,"Direction":0},{"Index":1,"PositionX":90,"PositionY":16,"Direction":0},{"Index":1,"PositionX":91,"PositionY":16,"Direction":0},{"Index":1,"PositionX":92,"PositionY":16,"Direction":0},{"Index":1,"PositionX":93,"PositionY":16,"Direction":0},{"Index":1,"PositionX":94,"PositionY":16,"Direction":0},{"Index":1,"PositionX":95,"PositionY":16,"Direction":0},{"Index":1,"PositionX":96,"PositionY":16,"Direction":0},{"Index":1,"PositionX":97,"PositionY":16,"Direction":0},{"Index":1,"PositionX":74,"PositionY":17,"Direction":0},{"Index":1,"PositionX":75,"PositionY":17,"Direction":0},{"Index":1,"PositionX":76,"PositionY":17,"Direction":0},{"Index":1,"PositionX":77,"PositionY":17,"Direction":0},{"Index":1,"PositionX":78,"PositionY":17,"Direction":0},{"Index":1,"PositionX":79,"PositionY":17,"Direction":0},{"Index":1,"PositionX":80,"PositionY":17,"Direction":0},{"Index":1,"PositionX":81,"PositionY":17,"Direction":0},{"Index":1,"PositionX":82,"PositionY":17,"Direction":0},{"Index":1,"PositionX":83,"PositionY":17,"Direction":0},{"Index":1,"PositionX":84,"PositionY":17,"Direction":0},{"Index":1,"PositionX":85,"PositionY":17,"Direction":0},{"Index":1,"PositionX":74,"PositionY":18,"Direction":0},{"Index":1,"PositionX":75,"PositionY":18,"Direction":0},{"Index":1,"PositionX":76,"PositionY":18,"Direction":0},{"Index":1,"PositionX":77,"PositionY":18,"Direction":0},{"Index":1,"PositionX":78,"PositionY":18,"Direction":0},{"Index":1,"PositionX":79,"PositionY":18,"Direction":0},{"Index":1,"PositionX":80,"PositionY":18,"Direction":0},{"Index":1,"PositionX":81,"PositionY":18,"Direction":0},{"Index":1,"PositionX":82,"PositionY":18,"Direction":0},{"Index":1,"PositionX":83,"PositionY":18,"Direction":0},{"Index":1,"PositionX":84,"PositionY":18,"Direction":0},{"Index":1,"PositionX":85,"PositionY":18,"Direction":0},{"Index":1,"PositionX":74,"PositionY":19,"Direction":0},{"Index":1,"PositionX":75,"PositionY":19,"Direction":0},{"Index":1,"PositionX":76,"PositionY":19,"Direction":0},{"Index":1,"PositionX":77,"PositionY":19,"Direction":0},{"Index":1,"PositionX":78,"PositionY":19,"Direction":0},{"Index":1,"PositionX":79,"PositionY":19,"Direction":0},{"Index":1,"PositionX":80,"PositionY":19,"Direction":0},{"Index":1,"PositionX":81,"PositionY":19,"Direction":0},{"Index":1,"PositionX":82,"PositionY":19,"Direction":0},{"Index":1,"PositionX":83,"PositionY":19,"Direction":0},{"Index":1,"PositionX":84,"PositionY":19,"Direction":0},{"Index":1,"PositionX":85,"PositionY":19,"Direction":0},{"Index":1,"PositionX":74,"PositionY":20,"Direction":0},{"Index":1,"PositionX":75,"PositionY":20,"Direction":0},{"Index":1,"PositionX":76,"PositionY":20,"Direction":0},{"Index":1,"PositionX":77,"PositionY":20,"Direction":0},{"Index":1,"PositionX":78,"PositionY":20,"Direction":0},{"Index":1,"PositionX":79,"PositionY":20,"Direction":0},{"Index":1,"PositionX":80,"PositionY":20,"Direction":0},{"Index":1,"PositionX":81,"PositionY":20,"Direction":0},{"Index":1,"PositionX":82,"PositionY":20,"Direction":0},{"Index":1,"PositionX":83,"PositionY":20,"Direction":0},{"Index":1,"PositionX":84,"PositionY":20,"Direction":0},{"Index":1,"PositionX":85,"PositionY":20,"Direction":0},{"Index":1,"PositionX":74,"PositionY":21,"Direction":0},{"Index":1,"PositionX":75,"PositionY":21,"Direction":0},{"Index":1,"PositionX":76,"PositionY":21,"Direction":0},{"Index":1,"PositionX":77,"PositionY":21,"Direction":0},{"Index":1,"PositionX":78,"PositionY":21,"Direction":0},{"Index":1,"PositionX":79,"PositionY":21,"Direction":0},{"Index":1,"PositionX":80,"PositionY":21,"Direction":0},{"Index":1,"PositionX":81,"PositionY":21,"Direction":0},{"Index":1,"PositionX":82,"PositionY":21,"Direction":0},{"Index":1,"PositionX":83,"PositionY":21,"Direction":0},{"Index":1,"PositionX":84,"PositionY":21,"Direction":0},{"Index":1,"PositionX":85,"PositionY":21,"Direction":0},{"Index":1,"PositionX":74,"PositionY":22,"Direction":0},{"Index":1,"PositionX":75,"PositionY":22,"Direction":0},{"Index":1,"PositionX":76,"PositionY":22,"Direction":0},{"Index":1,"PositionX":77,"PositionY":22,"Direction":0},{"Index":1,"PositionX":78,"PositionY":22,"Direction":0},{"Index":1,"PositionX":79,"PositionY":22,"Direction":0},{"Index":1,"PositionX":80,"PositionY":22,"Direction":0},{"Index":1,"PositionX":81,"PositionY":22,"Direction":0},{"Index":1,"PositionX":82,"PositionY":22,"Direction":0},{"Index":1,"PositionX":83,"PositionY":22,"Direction":0},{"Index":1,"PositionX":84,"PositionY":22,"Direction":0},{"Index":1,"PositionX":85,"PositionY":22,"Direction":0},{"Index":1,"PositionX":74,"PositionY":23,"Direction":0},{"Index":1,"PositionX":75,"PositionY":23,"Direction":0},{"Index":1,"PositionX":76,"PositionY":23,"Direction":0},{"Index":1,"PositionX":77,"PositionY":23,"Direction":0},{"Index":1,"PositionX":78,"PositionY":23,"Direction":0},{"Index":1,"PositionX":79,"PositionY":23,"Direction":0},{"Index":1,"PositionX":80,"PositionY":23,"Direction":0},{"Index":1,"PositionX":81,"PositionY":23,"Direction":0},{"Index":1,"PositionX":82,"PositionY":23,"Direction":0},{"Index":1,"PositionX":83,"PositionY":23,"Direction":0},{"Index":1,"PositionX":84,"PositionY":23,"Direction":0},{"Index":1,"PositionX":85,"PositionY":23,"Direction":0}]