[{"Index":1,"PositionX":49,"PositionY":23,"Direction":0},{"Index":1,"PositionX":52,"PositionY":26,"Direction":0},{"Index":1,"PositionX":47,"PositionY":22,"Direction":0},{"Index":1,"PositionX":47,"PositionY":23,"Direction":0},{"Index":1,"PositionX":47,"PositionY":24,"Direction":0},{"Index":1,"PositionX":53,"PositionY":27,"Direction":0},{"Index":1,"PositionX":48,"PositionY":22,"Direction":0},{"Index":1,"PositionX":48,"PositionY":23,"Direction":0},{"Index":1,"PositionX":48,"PositionY":24,"Direction":0},{"Index":1,"PositionX":49,"PositionY":21,"Direction":0},{"Index":1,"PositionX":49,"PositionY":22,"Direction":0},{"Index":1,"PositionX":49,"PositionY":24,"Direction":0},{"Index":1,"PositionX":50,"PositionY":21,"Direction":0},{"Index":1,"PositionX":50,"PositionY":22,"Direction":0},{"Index":1,"PositionX":50,"PositionY":23,"Direction":0},{"Index":1,"PositionX":50,"PositionY":24,"Direction":0},{"Index":1,"PositionX":53,"PositionY":26,"Direction":0},{"Index":1,"PositionX":54,"PositionY":25,"Direction":0},{"Index":1,"PositionX":52,"PositionY":27,"Direction":0},{"Index":1,"PositionX":51,"PositionY":20,"Direction":0},{"Index":1,"PositionX":51,"PositionY":21,"Direction":0},{"Index":1,"PositionX":51,"PositionY":22,"Direction":0},{"Index":1,"PositionX":51,"PositionY":23,"Direction":0},{"Index":1,"PositionX":51,"PositionY":24,"Direction":0},{"Index":1,"PositionX":52,"PositionY":21,"Direction":0},{"Index":1,"PositionX":52,"PositionY":22,"Direction":0},{"Index":1,"PositionX":52,"PositionY":23,"Direction":0},{"Index":1,"PositionX":52,"PositionY":24,"Direction":0},{"Index":1,"PositionX":50,"PositionY":25,"Direction":0},{"Index":1,"PositionX":48,"PositionY":25,"Direction":0},{"Index":1,"PositionX":48,"PositionY":26,"Direction":0},{"Index":1,"PositionX":49,"PositionY":25,"Direction":0},{"Index":1,"PositionX":49,"PositionY":26,"Direction":0},{"Index":1,"PositionX":50,"PositionY":26,"Direction":0},{"Index":1,"PositionX":51,"PositionY":25,"Direction":0},{"Index":1,"PositionX":51,"PositionY":26,"Direction":0},{"Index":1,"PositionX":52,"PositionY":20,"Direction":0},{"Index":1,"PositionX":53,"PositionY":20,"Direction":0},{"Index":1,"PositionX":53,"PositionY":21,"Direction":0},{"Index":1,"PositionX":53,"PositionY":22,"Direction":0},{"Index":1,"PositionX":53,"PositionY":23,"Direction":0},{"Index":1,"PositionX":52,"PositionY":25,"Direction":0},{"Index":1,"PositionX":53,"PositionY":24,"Direction":0},{"Index":1,"PositionX":53,"PositionY":25,"Direction":0},{"Index":1,"PositionX":54,"PositionY":26,"Direction":0},{"Index":1,"PositionX":54,"PositionY":27,"Direction":0},{"Index":1,"PositionX":54,"PositionY":24,"Direction":0},{"Index":1,"PositionX":54,"PositionY":23,"Direction":0},{"Index":1,"PositionX":54,"PositionY":22,"Direction":0},{"Index":1,"PositionX":51,"PositionY":27,"Direction":0}]