[
  {
    "Index": 410,
    "PositionX": 322,
    "PositionY": 124,
    "Direction": 0
  },
  {
    "Index": 410,
    "PositionX": 325,
    "PositionY": 129,
    "Direction": 0
  },
  {
    "Index": 410,
    "PositionX": 333,
    "PositionY": 123,
    "Direction": 0
  },
  {
    "Index": 410,
    "PositionX": 323,
    "PositionY": 113,
    "Direction": 0
  },
  {
    "Index": 410,
    "PositionX": 308,
    "PositionY": 117,
    "Direction": 0
  },
  {
    "Index": 410,
    "PositionX": 332,
    "PositionY": 132,
    "Direction": 0
  },
  {
    "Index": 410,
    "PositionX": 336,
    "PositionY": 135,
    "Direction": 0
  },
  {
    "Index": 410,
    "PositionX": 315,
    "PositionY": 131,
    "Direction": 0
  },
  {
    "Index": 410,
    "PositionX": 316,
    "PositionY": 123,
    "Direction": 0
  },
  {
    "Index": 410,
    "PositionX": 323,
    "PositionY": 105,
    "Direction": 0
  },
  {
    "Index": 410,
    "PositionX": 331,
    "PositionY": 116,
    "Direction": 0
  },
  {
    "Index": 410,
    "PositionX": 337,
    "PositionY": 129,
    "Direction": 0
  },
  {
    "Index": 410,
    "PositionX": 326,
    "PositionY": 137,
    "Direction": 0
  },
  {
    "Index": 410,
    "PositionX": 327,
    "PositionY": 108,
    "Direction": 0
  },
  {
    "Index": 410,
    "PositionX": 322,
    "PositionY": 133,
    "Direction": 0
  },
 
  {
    "Index": 410,
    "PositionX": 320,
    "PositionY": 119,
    "Direction": 0
  },
  {
    "Index": 410,
    "PositionX": 331,
    "PositionY": 138,
    "Direction": 0
  }
]
