[{"Index":220,"PositionX":48,"PositionY":145,"Direction":0},{"Index":220,"PositionX":43,"PositionY":185,"Direction":0},{"Index":220,"PositionX":26,"PositionY":183,"Direction":0},{"Index":220,"PositionX":31,"PositionY":162,"Direction":0},{"Index":220,"PositionX":86,"PositionY":225,"Direction":0},{"Index":220,"PositionX":90,"PositionY":230,"Direction":0},{"Index":220,"PositionX":89,"PositionY":221,"Direction":0},{"Index":220,"PositionX":84,"PositionY":230,"Direction":0},{"Index":220,"PositionX":82,"PositionY":222,"Direction":0},{"Index":220,"PositionX":173,"PositionY":233,"Direction":0},{"Index":220,"PositionX":164,"PositionY":223,"Direction":0},{"Index":220,"PositionX":164,"PositionY":231,"Direction":0},{"Index":220,"PositionX":174,"PositionY":225,"Direction":0},{"Index":220,"PositionX":169,"PositionY":228,"Direction":0},{"Index":220,"PositionX":218,"PositionY":196,"Direction":0},{"Index":220,"PositionX":219,"PositionY":190,"Direction":0},{"Index":220,"PositionX":214,"PositionY":191,"Direction":0},{"Index":220,"PositionX":223,"PositionY":194,"Direction":0},{"Index":220,"PositionX":221,"PositionY":106,"Direction":0},{"Index":220,"PositionX":224,"PositionY":114,"Direction":0},{"Index":220,"PositionX":226,"PositionY":106,"Direction":0},{"Index":220,"PositionX":228,"PositionY":111,"Direction":0},{"Index":220,"PositionX":224,"PositionY":108,"Direction":0},{"Index":220,"PositionX":223,"PositionY":53,"Direction":0},{"Index":220,"PositionX":223,"PositionY":58,"Direction":0},{"Index":220,"PositionX":218,"PositionY":54,"Direction":0},{"Index":220,"PositionX":217,"PositionY":57,"Direction":0},{"Index":220,"PositionX":211,"PositionY":53,"Direction":0},{"Index":220,"PositionX":157,"PositionY":28,"Direction":0},{"Index":220,"PositionX":155,"PositionY":32,"Direction":0},{"Index":220,"PositionX":145,"PositionY":27,"Direction":0},{"Index":220,"PositionX":148,"PositionY":31,"Direction":0},{"Index":220,"PositionX":152,"PositionY":26,"Direction":0},{"Index":220,"PositionX":104,"PositionY":24,"Direction":0},{"Index":220,"PositionX":95,"PositionY":30,"Direction":0},{"Index":220,"PositionX":96,"PositionY":25,"Direction":0},{"Index":220,"PositionX":96,"PositionY":22,"Direction":0},{"Index":220,"PositionX":100,"PositionY":30,"Direction":0},{"Index":220,"PositionX":100,"PositionY":25,"Direction":0},{"Index":220,"PositionX":45,"PositionY":37,"Direction":0},{"Index":220,"PositionX":48,"PositionY":45,"Direction":0},{"Index":220,"PositionX":42,"PositionY":41,"Direction":0},{"Index":220,"PositionX":47,"PositionY":40,"Direction":0},{"Index":220,"PositionX":51,"PositionY":40,"Direction":0},{"Index":220,"PositionX":30,"PositionY":83,"Direction":0},{"Index":220,"PositionX":31,"PositionY":89,"Direction":0},{"Index":220,"PositionX":27,"PositionY":88,"Direction":0},{"Index":220,"PositionX":24,"PositionY":82,"Direction":0},{"Index":220,"PositionX":22,"PositionY":85,"Direction":0},{"Index":220,"PositionX":48,"PositionY":138,"Direction":0},{"Index":220,"PositionX":46,"PositionY":141,"Direction":0},{"Index":220,"PositionX":44,"PositionY":137,"Direction":0},{"Index":220,"PositionX":41,"PositionY":145,"Direction":0}]