[{"Index":10025,"PositionX":78,"PositionY":219,"Direction":180},{"Index":10025,"PositionX":43,"PositionY":188,"Direction":90},{"Index":10015,"PositionX":38,"PositionY":218,"Direction":71},{"Index":10026,"PositionX":29,"PositionY":223,"Direction":117},{"Index":10025,"PositionX":57,"PositionY":205,"Direction":47},{"Index":10004,"PositionX":52,"PositionY":228,"Direction":190},{"Index":10027,"PositionX":33,"PositionY":240,"Direction":142},{"Index":10014,"PositionX":25,"PositionY":225,"Direction":110},{"Index":10011,"PositionX":21,"PositionY":219,"Direction":79},{"Index":10013,"PositionX":44,"PositionY":230,"Direction":158}]